efcFile/__init__.py
efcFile/interfaces/FileStorageInterface.py
efcFile/interfaces/__init__.py
efcFile/managers/FileStorageManager.py
efcFile/managers/__init__.py
efcFile/providers/LocalFileStorage.py
efcFile/providers/OSSFileStorage.py
efcFile/providers/QiniuFileStorage.py
efcFile/providers/S3FileStorage.py
efcFile/providers/__init__.py
efcFile-1.0.4.dist-info/METADATA
efcFile-1.0.4.dist-info/WHEEL
efcFile-1.0.4.dist-info/top_level.txt
efcFile-1.0.4.dist-info/RECORD
