Metadata-Version: 2.1
Name: efcFile
Version: 1.0.4
Summary: A file storage management package supporting various providers like S3, OSS, and Qiniu.
Home-page: https://github.com/duolabmeng6/efcFile
Author: duolabmeng6
Author-email: 1715109585@qq.com
Keywords: efcFile
Classifier: Programming Language :: Python :: 3
Classifier: License :: OSI Approved :: MIT License
Classifier: Operating System :: OS Independent
Requires-Python: >=3.6
